spltr/__init__.py
spltr/spltr.py
spltr/mods/__init__.py
spltr/mods/process_variable.py
spltr-0.3.2.dist-info/METADATA
spltr-0.3.2.dist-info/WHEEL
spltr-0.3.2.dist-info/top_level.txt
spltr-0.3.2.dist-info/RECORD
