Metadata-Version: 2.1
Name: spltr
Version: 0.3.2
Summary: A simple PyTorch-based data loader and splitter
Home-page: https://github.com/maksymsur/spltr
Author: Maksym Surzhynskyi
Author-email: maksym.surzhynskyi@gmail.com
License: UNKNOWN
Keywords: PyTorch,Data loader,Data splitter,DataLoader,random_split,train test,train test validation split,data preprocessing,pytorch dataset split
Platform: UNKNOWN
Classifier: Programming Language :: Python :: 3.6
Classifier: Programming Language :: Python :: 3.7
Classifier: Intended Audience :: Science/Research
Classifier: License :: OSI Approved :: MIT License
Classifier: Operating System :: OS Independent
Requires-Python: >=3.6
